Metadata-Version: 2.1
Name: deepmd-kit-cu11
Version: 3.1.2
Summary: A deep learning package for many-body potential energy representation and molecular dynamics
Keywords: deepmd
Author: DeepModeling
Author-Email: Han Wang <wang_han@iapcm.ac.cn>
License:                    GNU LESSER GENERAL PUBLIC LICENSE
Classifier: Natural Language :: English
Classifier: Operating System :: POSIX :: Linux
Classifier: Operating System :: Microsoft :: Windows
Classifier: Development Status :: 5 - Production/Stable
Classifier: Programming Language :: C
Classifier: Programming Language :: C++
Classifier: Programming Language :: Python :: 3 :: Only
Classifier: Environment :: GPU :: NVIDIA CUDA :: 12 :: 12.2
Classifier: Intended Audience :: Science/Research
Classifier: Programming Language :: Python :: 3.9
Classifier: Programming Language :: Python :: 3.10
Classifier: Programming Language :: Python :: 3.11
Classifier: Programming Language :: Python :: 3.12
Classifier: License :: OSI Approved :: GNU Lesser General Public License v3 (LGPLv3)
Classifier: Topic :: Scientific/Engineering :: Artificial Intelligence
Classifier: Topic :: Scientific/Engineering :: Physics
Classifier: Topic :: Scientific/Engineering :: Chemistry
Classifier: Environment :: Console
Project-URL: Homepage, https://github.com/deepmodeling/deepmd-kit
Project-URL: documentation, https://docs.deepmodeling.com/projects/deepmd
Project-URL: repository, https://github.com/deepmodeling/deepmd-kit
Requires-Python: >=3.9
Requires-Dist: numpy>=1.21
Requires-Dist: scipy
Requires-Dist: pyyaml
Requires-Dist: dargs>=0.4.7
Requires-Dist: typing_extensions; python_version < "3.8"
Requires-Dist: importlib_metadata>=1.4; python_version < "3.8"
Requires-Dist: h5py
Requires-Dist: h5py!=3.11.0,>=3.6.0; platform_system == "Linux" and platform_machine == "aarch64"
Requires-Dist: wcmatch
Requires-Dist: packaging
Requires-Dist: ml_dtypes
Requires-Dist: mendeleev
Requires-Dist: array-api-compat
Provides-Extra: test
Requires-Dist: dpdata>=0.2.7; extra == "test"
Requires-Dist: ase>=3.23.0; extra == "test"
Requires-Dist: pytest; extra == "test"
Requires-Dist: pytest-cov; extra == "test"
Requires-Dist: pytest-sugar; extra == "test"
Requires-Dist: pytest-split; extra == "test"
Requires-Dist: dpgui; extra == "test"
Requires-Dist: array-api-strict!=2.1.1,>=2; python_version >= "3.9" and extra == "test"
Provides-Extra: docs
Requires-Dist: sphinx>=3.1.1; extra == "docs"
Requires-Dist: sphinx-book-theme; extra == "docs"
Requires-Dist: myst-nb>=1.0.0; extra == "docs"
Requires-Dist: myst-parser>=0.19.2; extra == "docs"
Requires-Dist: sphinx-design; extra == "docs"
Requires-Dist: breathe; extra == "docs"
Requires-Dist: exhale>=0.3.7; extra == "docs"
Requires-Dist: numpydoc; extra == "docs"
Requires-Dist: ase; extra == "docs"
Requires-Dist: deepmodeling-sphinx>=0.3.0; extra == "docs"
Requires-Dist: dargs>=0.3.4; extra == "docs"
Requires-Dist: sphinx-argparse<0.5.0; extra == "docs"
Requires-Dist: pygments-lammps; extra == "docs"
Requires-Dist: sphinxcontrib-bibtex; extra == "docs"
Requires-Dist: sphinx-autoapi>=3.0.0; extra == "docs"
Requires-Dist: sphinxcontrib-programoutput; extra == "docs"
Requires-Dist: sphinxcontrib-moderncmakedomain; extra == "docs"
Requires-Dist: sphinx-remove-toctrees; extra == "docs"
Provides-Extra: lmp
Requires-Dist: lammps[mpi]~=2025.7.22.2.0; extra == "lmp"
Provides-Extra: ipi
Requires-Dist: ipi; extra == "ipi"
Provides-Extra: gui
Requires-Dist: dpgui; extra == "gui"
Provides-Extra: cu11
Requires-Dist: nvidia-cuda-runtime-cu11; extra == "cu11"
Requires-Dist: nvidia-cublas-cu11; extra == "cu11"
Requires-Dist: nvidia-cufft-cu11; extra == "cu11"
Requires-Dist: nvidia-curand-cu11; extra == "cu11"
Requires-Dist: nvidia-cusolver-cu11; extra == "cu11"
Requires-Dist: nvidia-cusparse-cu11; extra == "cu11"
Requires-Dist: nvidia-cudnn-cu11<9; extra == "cu11"
Requires-Dist: nvidia-cuda-nvcc-cu11; extra == "cu11"
Provides-Extra: cu12
Requires-Dist: nvidia-cuda-runtime-cu12; extra == "cu12"
Requires-Dist: nvidia-cublas-cu12; extra == "cu12"
Requires-Dist: nvidia-cufft-cu12; extra == "cu12"
Requires-Dist: nvidia-curand-cu12; extra == "cu12"
Requires-Dist: nvidia-cusolver-cu12; extra == "cu12"
Requires-Dist: nvidia-cusparse-cu12; extra == "cu12"
Requires-Dist: nvidia-cudnn-cu12; extra == "cu12"
Requires-Dist: nvidia-cuda-nvcc-cu12; extra == "cu12"
Provides-Extra: jax
Requires-Dist: jax>=0.4.33; python_version >= "3.10" and extra == "jax"
Requires-Dist: jax>=0.4.33; python_version >= "3.10" and extra == "jax"
Requires-Dist: flax>=0.10.0; python_version >= "3.10" and extra == "jax"
Requires-Dist: flax>=0.10.0; python_version >= "3.10" and extra == "jax"
Requires-Dist: orbax-checkpoint; python_version >= "3.10" and extra == "jax"
Requires-Dist: orbax-checkpoint; python_version >= "3.10" and extra == "jax"
Provides-Extra: cpu
Requires-Dist: tensorflow-cpu==2.14.1; platform_machine != "aarch64" and (platform_machine != "arm64" or platform_system != "Darwin") and extra == "cpu"
Requires-Dist: tensorflow==2.14.1; (platform_machine == "aarch64" or (platform_machine == "arm64" and platform_system == "Darwin")) and extra == "cpu"
Provides-Extra: gpu
Requires-Dist: tensorflow==2.14.1; extra == "gpu"
Requires-Dist: tensorflow-metal; platform_machine == "arm64" and platform_system == "Darwin" and extra == "gpu"
Provides-Extra: mpi
Requires-Dist: horovod; extra == "mpi"
Requires-Dist: mpi4py; extra == "mpi"
Provides-Extra: torch
Requires-Dist: torch==2.3.1.*; extra == "torch"
Requires-Dist: mpich; extra == "torch"
